./.gitignore
./PKG-INFO
./README.md
./bnf_server.py
./language.json
./package_name
./pyproject.toml
./requirements.txt
./bnf_api/__init__.py
./bnf_api/api.py
./bnf_api/config.py
./bnf_api/search.py
./bnf_api/sequential_reporting.py
iflow_mcp_kryzo_mcp_bibliotheque_nationale_de_france-1.0.0.dist-info/METADATA
iflow_mcp_kryzo_mcp_bibliotheque_nationale_de_france-1.0.0.dist-info/WHEEL
iflow_mcp_kryzo_mcp_bibliotheque_nationale_de_france-1.0.0.dist-info/entry_points.txt
iflow_mcp_kryzo_mcp_bibliotheque_nationale_de_france-1.0.0.dist-info/RECORD
