Metadata-Version: 2.4
Name: iflow-mcp_kryzo_mcp-bibliotheque_nationale_de_france
Version: 1.0.0
Summary: MCP server for accessing the Gallica API of the Bibliothèque nationale de France (BnF)
Requires-Python: >=3.8
Requires-Dist: fastmcp>=0.1.0
Requires-Dist: requests>=2.31.0
